hash/__init__.py
hash/dag.py
hash/errors.py
hash/logs.py
hash/utils.py
hash/cli/__init__.py
hash/cli/main.py
hash/kern/__init__.py
hash/kern/action.py
hash/kern/execute.py
hash/kern/hash.py
hash/kern/main.py
hash/kern/planner.py
hash/kern/secrets.py
hash/kern/state.py
hash/kern/templates.py
hash/resources/__init__.py
hash/resources/base.py
hash/resources/targets.py
hash/store/__init__.py
hash/store/base.py
hashkern-0.4.0.dist-info/LICENSE
hashkern-0.4.0.dist-info/METADATA
hashkern-0.4.0.dist-info/WHEEL
hashkern-0.4.0.dist-info/entry_points.txt
hashkern-0.4.0.dist-info/top_level.txt
hashkern-0.4.0.dist-info/RECORD
