Metadata-Version: 2.1
Name: hashkern
Version: 0.4.0
Summary: A tool for managing resources in a mono repository
Author: Mouhsen Ibrahim
Author-email: mouhsen.ibrahim@gmail.com
Project-URL: Documentation, https://hash-kern.readthedocs.io/en/latest/index.html
Project-URL: Source, https://gitlab.com/hash-platform/hashkern
Classifier: Development Status :: 2 - Pre-Alpha
Classifier: Environment :: Console
Classifier: Intended Audience :: Developers
Classifier: Topic :: Software Development
Classifier: Programming Language :: Python :: 3
Classifier: License :: OSI Approved :: Apache Software License
Classifier: Operating System :: OS Independent
Requires-Python: >=3.7
License-File: LICENSE
Requires-Dist: dirhash (~=0.2.1)
Requires-Dist: wheel (~=0.38.4)
Requires-Dist: setuptools (~=65.6.3)
Requires-Dist: google-cloud-storage (~=2.7.0)
Requires-Dist: pluggy (~=1.0.0)
Requires-Dist: boto3 (~=1.26.45)
Requires-Dist: pyyaml (~=5.3)
Requires-Dist: graphviz (~=0.20.1)
Requires-Dist: hvac (~=1.1.0)
Requires-Dist: google-cloud-secret-manager (~=2.16.1)
Requires-Dist: requests (~=2.28.2)
Requires-Dist: Jinja2 (==3.1.2)
